clustools/__init__.py
clustools/cluster/__init__.py
clustools/cluster/_faiss.py
clustools/cluster/_fuzzy.py
clustools/cluster/custom_cluster_mixin.py
clustools/metrics/__init__.py
clustools/metrics/external.py
clustools/metrics/internal.py
clustools/metrics/selection.py
clustools/pairwise/__init__.py
clustools/pairwise/agreement.py
clustools/pairwise/consensus.py
clustools/pairwise/distances.py
clustools/pairwise/summary.py
clustools/py.typed
clustools/utils/__init__.py
clustools/utils/cluster_centers.py
clustools/utils/constants.py
clustools/utils/labels.py
clustools/utils/matrices.py
clustools-0.3.2.dist-info/licenses/LICENSE
clustools-0.3.2.dist-info/WHEEL
clustools-0.3.2.dist-info/METADATA
clustools-0.3.2.dist-info/RECORD
