Metadata-Version: 2.4
Name: clustools
Version: 0.3.2
Summary: A lightweight Python package providing essential clustering utilities for clustering workflows.
Keywords: clustools
Author: Pablo Solís-Fernández
Author-email: Pablo Solís-Fernández <psolsfer@gmail.com>
License-Expression: BSD-3-Clause
License-File: LICENSE
Classifier: Development Status :: 2 - Pre-Alpha
Classifier: Intended Audience :: Developers
Classifier: License :: OSI Approved :: BSD License
Classifier: Natural Language :: English
Classifier: Programming Language :: Python :: 3
Classifier: Programming Language :: Python :: 3.12
Classifier: Programming Language :: Python :: 3.13
Requires-Dist: faiss-cpu>=1.12.0
Requires-Dist: numpy>=2.0.0
Requires-Dist: pyauxlib>=0.13.0
Requires-Dist: scikit-fuzzy>=0.5.0
Requires-Dist: scikit-learn>=1.6
Requires-Dist: scipy>=1.16.1
Requires-Python: >=3.12, <3.14
Project-URL: Documentation, https://clustools.readthedocs.io
Project-URL: Homepage, https://github.com/psolsfer/clustools
Project-URL: Issues, https://github.com/psolsfer/clustools/issues
Project-URL: Repository, https://github.com/psolsfer/clustools
